cbbuild/__init__.py
cbbuild/database/__init__.py
cbbuild/database/db.py
cbbuild_database-0.8.1.dist-info/METADATA
cbbuild_database-0.8.1.dist-info/WHEEL
cbbuild_database-0.8.1.dist-info/RECORD
