Metadata-Version: 2.3
Name: cbbuild-database
Version: 0.8.1
Summary: Couchbase Build Team build database package
Author-email: Couchbase Build Team <build-team@couchbase.com>
License: Apache License, Version 2.0
Requires-Python: <4,>=3.10
Requires-Dist: couchbase>=4
